pyleadfinder/__init__.py
pyleadfinder/errors.py
pyleadfinder/maps.py
pyleadfinder/models.py
pyleadfinder/places.py
pyleadfinder/rate_limiter.py
pyleadfinder/scraper.py
pyleadfinder/session.py
pyleadfinder/zip_optimizer.py
pyleadfinder-0.1.0.dist-info/licenses/LICENSE
pyleadfinder-0.1.0.dist-info/METADATA
pyleadfinder-0.1.0.dist-info/WHEEL
pyleadfinder-0.1.0.dist-info/top_level.txt
pyleadfinder-0.1.0.dist-info/RECORD
